ecogvis/__init__.py
ecogvis/ecogvis.py
ecogvis/functions/FS_colorLUT.py
ecogvis/functions/__init__.py
ecogvis/functions/audio_event_detection.py
ecogvis/functions/event_related_potential.py
ecogvis/functions/misc_dialogs.py
ecogvis/functions/nwb_copy_file.py
ecogvis/functions/save_to_nwb.py
ecogvis/functions/subFunctions.py
ecogvis/functions/survey_data.py
ecogvis/functions/transcription_data.py
ecogvis/functions/htk_to_nwb/HTK.py
ecogvis/functions/htk_to_nwb/__init__.py
ecogvis/functions/htk_to_nwb/chang2nwb.py
ecogvis/functions/test/__init__.py
ecogvis/functions/test/test_nwb_copy_file.py
ecogvis/signal_processing/__init__.py
ecogvis/signal_processing/bands.py
ecogvis/signal_processing/common_referencing.py
ecogvis/signal_processing/detect_events.py
ecogvis/signal_processing/hilbert_transform.py
ecogvis/signal_processing/periodogram.py
ecogvis/signal_processing/processing_data.py
ecogvis/signal_processing/zscore.py
ecogvis/ui/__init__.py
ecogvis/ui/exit_gui.ui
ecogvis/ui/high_gamma_gui.ui
ecogvis/ui/intervals_gui.ui
ecogvis/ui/preprocessing_gui.ui
ecogvis/ui/spectral_choice_gui.ui
ecogvis-1.2.2.dist-info/LICENSE
ecogvis-1.2.2.dist-info/METADATA
ecogvis-1.2.2.dist-info/WHEEL
ecogvis-1.2.2.dist-info/entry_points.txt
ecogvis-1.2.2.dist-info/top_level.txt
ecogvis-1.2.2.dist-info/RECORD
