Metadata-Version: 2.1
Name: ecogvis
Version: 1.2.2
Summary: Timeseries visualizer for Electrocorticography (ECoG) signals stored in NWB files.
Home-page: https://github.com/catalystneuro/ecogVIS
Author: Luiz Tauffer and Ben Dichter
License: UNKNOWN
Platform: UNKNOWN
Requires-Dist: PyQt5
Requires-Dist: matplotlib
Requires-Dist: cycler
Requires-Dist: scipy
Requires-Dist: numpy
Requires-Dist: h5py
Requires-Dist: pyqtgraph
Requires-Dist: pandas
Requires-Dist: pynwb (>=1.1.2)
Requires-Dist: PyYAML
Requires-Dist: ndx-ecog
Requires-Dist: ndx-spectrum
Requires-Dist: ndx-survey-data
Requires-Dist: ndx-bipolar-scheme
Requires-Dist: tqdm
Requires-Dist: pyopengl
Requires-Dist: process-nwb
Requires-Dist: PyQtWebEngine
Requires-Dist: ndx-icephys-meta
Requires-Dist: ndx-hierarchical-behavioral-data
